Metadata-Version: 1.0
Name: formfiller
Version: 0.4
Summary: Create images of filled-out forms
Home-page: https://github.com/BlueprintKansas/form-filler-py
Author: Peter Karman
Author-email: peter@peknet.com
License: MIT
Platform: UNKNOWN
